alissonSomav4/__init__.py
alissonSomav4/somav2.py
alissonSomav4-0.1.dist-info/LICENSE
alissonSomav4-0.1.dist-info/METADATA
alissonSomav4-0.1.dist-info/WHEEL
alissonSomav4-0.1.dist-info/top_level.txt
alissonSomav4-0.1.dist-info/RECORD
