Metadata-Version: 2.1
Name: alissonSomav4
Version: 0.1
Summary: Pacote simples de soma
Home-page: https://github.com/Alisson-Rodrigo
Author: Alisson
License: MIT
Platform: UNKNOWN
License-File: LICENSE
